Workbook

Sheet Mode d'emploi
B2: Matrice de restitution des verbatims
B3: Memoire MAE - Arthur Saunier - Wavestone Luxembourg
B5: Principe | C5: Une seule saisie : l'onglet Verbatims. Tout le reste se calcule automatiquement.
B7: 1. Panel | C7: Renseigner les repondants avant le premier entretien : code, profil, fonction, date. Les codes de cet onglet alimentent les listes deroulantes et les colonnes de la matrice.
B8: 2. Codebook | C8: La grille de codage, adossee aux quatre questions directrices. Les codes E3.x sont ouverts : les intituler au fur et a mesure si un theme non anticipe emerge.
B9: 3. Verbatims | C9: Onglet de travail. Une ligne = un segment de sens code. Coller l'extrait, choisir le repondant et le code dans les listes deroulantes. Un meme extrait porteur de deux idees se saisit sur deux lignes.
B10: 4. Matrice | C10: Croisement automatique codes x repondants. Lecture en ligne : convergences et clivages du panel. Lecture en colonne : coherence interne du discours d'un repondant.
B11: 5. Synthese J/M | C11: Comparaison juniors / managers, code par code. L'ecart signale les points ou le terrain produit un resultat, et alimente directement la section 4.1 du memoire.
B12: 6. Saturation | C12: Suivi du nombre de codes nouveaux apportes par chaque entretien. La saturation est atteinte quand un entretien supplementaire n'ajoute plus de code.
B14: Cellules a saisir | C14: En bleu. Toutes les autres contiennent des formules : ne pas les ecraser.
B15: Anonymisation | C15: Ne jamais saisir de nom de personne, de client ou de mission. Utiliser [client], [mission], [collegue].
B16: Version preremplie
C17: Les colonnes Repondant, Verbatim, Contexte et Theme sont deja renseignees a partir des cinq prises de notes. Il ne reste qu'a saisir la colonne C (Code), en s'aidant de la grille de l'onglet Codebook.
C18: Un meme segment peut recevoir plusieurs codes : dupliquer la ligne et changer le code. Un segment sans code pertinent : supprimer la ligne.
C19: Les noms d'outils commerciaux sont remplaces par des designations generiques entre crochets, conformement a la regle du memoire.
C20: Deux lignes marquees ### A COMPLETER signalent des passages du corpus non repris : les remplacer a partir des fichiers interviews/e2.tex et interviews/e3.tex.
C21: Ne rien saisir dans les onglets Matrice, Synthese J-M et Saturation : ils se recalculent seuls.

Sheet Panel
A1: Panel des repondants
A3: Code | B3: Profil | C3: Fonction | D3: Anciennete conseil (annees) | E3: Date entretien | F3: Duree (min) | G3: Enregistre (O/N) | H3: Notes de contexte
A4: J1 | B4: Junior | C4: Stagiaire | D4: 0 | G4: N | H4: 5 mois - propales, institutions europeennes
A5: J2 | B5: Junior | C5: Analyste | D5: 0 | G5: N | H5: 6 mois - gestion de crise, appels d offre
A6: J3 | B6: Junior | C6: (non pourvu) | H6: Colonne laissee vide
A7: J4 | B7: Junior | C7: (non pourvu) | H7: Colonne laissee vide
A8: E1 | B8: Encadrant | C8: Manager | D8: 10 | G8: N | H8: Banque, assurance, institutions europeennes
A9: E2 | B9: Encadrant | C9: Associate Partner | D9: 25 | G9: N | H9: Institutions europeennes, sponsor Data & AI
A10: E3 | B10: Encadrant | C10: Consultant senior | D10: 3 | G10: N | H10: Cybersecurite, institution europeenne
A11: E4 | B11: Encadrant | C11: (non pourvu) | H11: Colonne laissee vide
A13: Profils : Junior (analyste, consultant) / Encadrant (du consultant senior a l'associe).
A14: Les deux positions correspondent aux deux côtés du dispositif de revue : qui rédige, qui contrôle.

Sheet Codebook
A1: Grille d'analyse thematique
A3: Code | B3: Intitule | C3: Definition / critere d'affectation | D3: Question directrice | E3: Ancrage theorique
A4: Axe A | B4: Appropriation des outils dans le travail d'analyse
A5: A1.1 | B5: Recherche et veille | C5: Delegation de la recherche documentaire, reglementaire ou sectorielle | D5: QD1 - Appropriation reelle | E5: Sociologie des usages ; TAM (Davis, 1989)
A6: A1.2 | B6: Synthese et reformulation | C6: Condensation ou reecriture d'un materiau existant | D6: QD1 - Appropriation reelle | E6: Sociologie des usages ; TAM (Davis, 1989)
A7: A1.3 | B7: Premiere redaction | C7: Production d'un premier jet de livrable ou de section | D7: QD1 - Appropriation reelle | E7: Sociologie des usages ; TAM (Davis, 1989)
A8: A1.4 | B8: Traduction et mise en forme | C8: Travail linguistique ou formel sans production analytique | D8: QD1 - Appropriation reelle | E8: Sociologie des usages ; TAM (Davis, 1989)
A9: A1.5 | B9: Structuration du raisonnement | C9: Aide a la construction d'un plan ou d'une problematique | D9: QD1 - Appropriation reelle | E9: Sociologie des usages ; TAM (Davis, 1989)
A10: A2.1 | B10: Sanctuarisation - confidentialite | C10: Tache non deleguee en raison de la sensibilite des donnees | D10: QD1 - Appropriation reelle | E10: Sociologie des usages ; TAM (Davis, 1989)
A11: A2.2 | B11: Sanctuarisation - jugement | C11: Tache non deleguee car jugee exiger un jugement professionnel | D11: QD1 - Appropriation reelle | E11: Sociologie des usages ; TAM (Davis, 1989)
A12: A2.3 | B12: Sanctuarisation - relation | C12: Tache non deleguee car relevant de l'interaction client | D12: QD1 - Appropriation reelle | E12: Sociologie des usages ; TAM (Davis, 1989)
A13: A3.1 | B13: Apprentissage autonome | C13: Montee en competence sur l'outil par essai personnel | D13: QD1 - Appropriation reelle | E13: Sociologie des usages ; TAM (Davis, 1989)
A14: A3.2 | B14: Transmission entre pairs | C14: Apprentissage horizontal, informel, au sein de l'equipe | D14: QD1 - Appropriation reelle | E14: Sociologie des usages ; TAM (Davis, 1989)
A15: A3.3 | B15: Formation institutionnelle | C15: Dispositif de formation porte par le cabinet | D15: QD1 - Appropriation reelle | E15: Sociologie des usages ; TAM (Davis, 1989)
A16: A4.1 | B16: Utilite percue | C16: Benefice attendu exprime en termes de performance (TAM) | D16: QD1 - Appropriation reelle | E16: Sociologie des usages ; TAM (Davis, 1989)
... A19: A4.4 | B19: Contournement outille | C19: Recours a un outil personnel hors du cadre officiel | D19: QD1 - Appropriation reelle | E19: Sociologie des usages ; TAM (Davis, 1989)
A20: Axe B | B20: Apprentissage, competences et transmission
A21: B1.1 | B21: Vertu formatrice reconnue | C21: Tache ingrate decrite comme pedagogiquement necessaire | D21: QD2 - Impact sur les competences | E21: Polanyi (1966) ; Nonaka & Takeuchi (1995)
A22: B1.2 | B22: Vertu formatrice deniee | C22: Tache ingrate decrite comme sans apport d'apprentissage | D22: QD2 - Impact sur les competences | E22: Polanyi (1966) ; Nonaka & Takeuchi (1995)
A23: B2.1 | B23: Acceleration de la montee en competence | C23: Progression jugee plus rapide grace a l'outil | D23: QD2 - Impact sur les competences | E23: Polanyi (1966) ; Nonaka & Takeuchi (1995)
A24: B2.2 | B24: Atrophie du raisonnement | C24: Perte declaree ou observee de capacite d'analyse autonome | D24: QD2 - Impact sur les competences | E24: Polanyi (1966) ; Nonaka & Takeuchi (1995)
A25: B2.3 | B25: Verification comme competence | C25: Emergence du controle critique comme savoir-faire propre | D25: QD2 - Impact sur les competences | E25: Polanyi (1966) ; Nonaka & Takeuchi (1995)
A26: B3.1 | B26: Relecture senior formatrice | C26: La revue hierarchique decrite comme moment de transmission | D26: QD2 - Impact sur les competences | E26: Polanyi (1966) ; Nonaka & Takeuchi (1995)
A27: B3.2 | B27: Appauvrissement de l'interaction | C27: Reduction des echanges junior-senior imputee a l'outil | D27: QD2 - Impact sur les competences | E27: Polanyi (1966) ; Nonaka & Takeuchi (1995)
A28: B3.3 | B28: Compagnonnage preserve | C28: Maintien affirme des mecanismes traditionnels de socialisation | D28: QD2 - Impact sur les competences | E28: Polanyi (1966) ; Nonaka & Takeuchi (1995)
A29: B4.1 | B29: Dependance declaree | C29: Difficulte exprimee a travailler sans l'outil | D29: QD2 - Impact sur les competences | E29: Polanyi (1966) ; Nonaka & Takeuchi (1995)
A30: B4.2 | B30: Validation sans maitrise | C30: Approbation d'un contenu que le repondant ne saurait produire | D30: QD2 - Impact sur les competences | E30: Polanyi (1966) ; Nonaka & Takeuchi (1995)
A31: Axe C | B31: Legitimite de l'expert et relation client
A32: C1.1 | B32: Legitimite cognitive | C32: Confiance fondee sur l'expertise et la maitrise du domaine | D32: QD3 - Legitimite de l'expert | E32: Abbott (1988) ; Suchman (1995)
A33: C1.2 | B33: Legitimite pragmatique | C33: Confiance fondee sur l'utilite et le resultat obtenu | D33: QD3 - Legitimite de l'expert | E33: Abbott (1988) ; Suchman (1995)
A34: C1.3 | B34: Legitimite morale | C34: Confiance fondee sur la responsabilite assumee et la deontologie | D34: QD3 - Legitimite de l'expert | E34: Abbott (1988) ; Suchman (1995)
A35: C2.1 | B35: Transparence assumee | C35: Usage de l'outil declare au client | D35: QD3 - Legitimite de l'expert | E35: Abbott (1988) ; Suchman (1995)
A36: C2.2 | B36: Opacite strategique | C36: Usage deliberement non declare | D36: QD3 - Legitimite de l'expert | E36: Abbott (1988) ; Suchman (1995)
A37: C2.3 | B37: Interpellation par le client | C37: Le client souleve lui-meme la question de l'usage | D37: QD3 - Legitimite de l'expert | E37: Abbott (1988) ; Suchman (1995)
A38: C3.1 | B38: Deplacement vers le jugement | C38: Valeur du cabinet redefinie autour du sens critique | D38: QD3 - Legitimite de l'expert | E38: Abbott (1988) ; Suchman (1995)
A39: C3.2 | B39: Deplacement vers la responsabilite | C39: Valeur du cabinet redefinie autour de l'engagement pris | D39: QD3 - Legitimite de l'expert | E39: Abbott (1988) ; Suchman (1995)
A40: C3.3 | B40: Menace de desintermediation | C40: Crainte que le client produise l'analyse par lui-meme | D40: QD3 - Legitimite de l'expert | E40: Abbott (1988) ; Suchman (1995)
A41: C4.1 | B41: Tension sur le modele tarifaire | C41: Remise en cause de la facturation au temps passe | D41: QD3 - Legitimite de l'expert | E41: Abbott (1988) ; Suchman (1995)
A42: Axe D | B42: Gouvernance, controle qualite et risques
A43: D1.1 | B43: Regle formelle connue | C43: Reference a une politique explicite du cabinet | D43: QD4 - Gouvernance et risques | E43: Mintzberg (1982) ; gouvernance des risques
A44: D1.2 | B44: Norme informelle | C44: Regle d'equipe non ecrite, transmise oralement | D44: QD4 - Gouvernance et risques | E44: Mintzberg (1982) ; gouvernance des risques
A45: D1.3 | B45: Flou normatif | C45: Meconnaissance ou incertitude sur le cadre applicable | D45: QD4 - Gouvernance et risques | E45: Mintzberg (1982) ; gouvernance des risques
A46: D2.1 | B46: Revue hierarchique | C46: Controle du livrable par un niveau superieur | D46: QD4 - Gouvernance et risques | E46: Mintzberg (1982) ; gouvernance des risques
A47: D2.2 | B47: Verification des sources | C47: Controle specifique de la veracite du contenu produit | D47: QD4 - Gouvernance et risques | E47: Mintzberg (1982) ; gouvernance des risques
A48: D2.3 | B48: Absence de controle dedie | C48: Aucun dispositif specifique au contenu genere | D48: QD4 - Gouvernance et risques | E48: Mintzberg (1982) ; gouvernance des risques
A49: D3.1 | B49: Hallucination detectee | C49: Incident avere de contenu errone identifie a temps | D49: QD4 - Gouvernance et risques | E49: Mintzberg (1982) ; gouvernance des risques
A50: D3.2 | B50: Quasi-incident | C50: Erreur passee pres d'atteindre le client | D50: QD4 - Gouvernance et risques | E50: Mintzberg (1982) ; gouvernance des risques
A51: D3.3 | B51: Enjeu de confidentialite | C51: Risque de divulgation de donnees de mission | D51: QD4 - Gouvernance et risques | E51: Mintzberg (1982) ; gouvernance des risques
A52: D4.1 | B52: Attribution de responsabilite | C52: Designation de qui repond de l'erreur | D52: QD4 - Gouvernance et risques | E52: Mintzberg (1982) ; gouvernance des risques
A53: D5.1 | B53: Regle percue comme bridante | C53: Cadre juge contraignant au regard du travail reel | D53: QD4 - Gouvernance et risques | E53: Mintzberg (1982) ; gouvernance des risques
A54: D5.2 | B54: Demande de cadrage | C54: Souhait exprime d'un encadrement plus explicite | D54: QD4 - Gouvernance et risques | E54: Mintzberg (1982) ; gouvernance des risques
A55: Axe T | B55: Codes transversaux et emergents
A56: T1.1 | B56: Ecart discours-pratique | C56: Contradiction interne entre position declaree et pratique decrite | D56: Transversal | E56: ---
A57: T1.2 | B57: Ecart junior-encadrant | C57: Divergence de perception entre les deux positions sur un meme objet | D57: Transversal | E57: ---
A58: T2.1 | B58: Prospective du metier | C58: Projection sur l'evolution du conseil a moyen terme | D58: Transversal | E58: ---
A59: T2.2 | B59: Recommandation spontanee | C59: Proposition d'action formulee par le repondant | D59: Transversal | E59: ---
A60: T3.1 | B60: Le non-dit interne | C60: Usage de l'outil passe sous silence entre collegues, independamment du client | D60: Transversal | E60: ---
A61: T3.2 | B61: L'incident declencheur de controle | C61: Modification d'une pratique de revue consecutive a une erreur vecue | D61: Transversal | E61: ---
A62: T3.3 | B62: Avantage commercial | C62: Utilisation de l'IA amène à un avantage sur le marché | D62: Transversal | E62: ---

Sheet Verbatims
A1: Corpus code - onglet de saisie
A2: Une ligne = un segment de sens. Colonnes bleues a saisir ; la colonne Profil se calcule.
A4: Repondant | B4: Profil | C4: Code | D4: Intitule du code | E4: Verbatim (anonymise) | F4: Contexte / mission evoquee | G4: Remarque d'analyse | H4: Theme (repere)
A5: J1 | B5: =IFERROR(INDEX(Panel!$B$4:$B$11,MATCH($A5,Panel!$A$4:$A$11,0)),"") | C5: A1.5 | D5: =IFERROR(INDEX(Codebook!$B$4:$B$62,MATCH($C5,Codebook!$A$4:$A$62,0)),"") | E5: Semaine dernière. Propale. 10 slides sur sujet que maîtrisais moyennement. [Outil homologué] direct dans PPT. Demandé structure titres/sous-parties sur 3 docs. | F5: Propale | H5: T1
A6: J1 | B6: =IFERROR(INDEX(Panel!$B$4:$B$11,MATCH($A6,Panel!$A$4:$A$11,0)),"") | C6: A4.1 | D6: =IFERROR(INDEX(Codebook!$B$4:$B$62,MATCH($C6,Codebook!$A$4:$A$62,0)),"") | E6: 5 min contre 1h à tout relire. Après, j'ai repris chaque slide. Contenu générique mais squelette sympa. J'ai mis la viande autour. | F6: Propale | H6: T1
A7: J1 | B7: =IFERROR(INDEX(Panel!$B$4:$B$11,MATCH($A7,Panel!$A$4:$A$11,0)),"") | C7: A1.2 | D7: =IFERROR(INDEX(Codebook!$B$4:$B$62,MATCH($C7,Codebook!$A$4:$A$62,0)),"") | E7: Tout le temps : reformulation. Notes réunion fouillis -> « rends-moi structuré ». Là-dessus c'est un tueur. | H7: T1
A8: J1 | B8: =IFERROR(INDEX(Panel!$B$4:$B$11,MATCH($A8,Panel!$A$4:$A$11,0)),"") | C8: A1.4 | D8: =IFERROR(INDEX(Codebook!$B$4:$B$62,MATCH($C8,Codebook!$A$4:$A$62,0)),"") | E8: Traductions aussi. Anglais/français. | H8: T1
A9: J1 | B9: =IFERROR(INDEX(Panel!$B$4:$B$11,MATCH($A9,Panel!$A$4:$A$11,0)),"") | C9: A2.1 | D9: =IFERROR(INDEX(Codebook!$B$4:$B$62,MATCH($C9,Codebook!$A$4:$A$62,0)),"") | E9: Jamais sur slides avec données chiffrées confidentielles. Dealbreaker. | H9: T1
A10: J1 | B10: =IFERROR(INDEX(Panel!$B$4:$B$11,MATCH($A10,Panel!$A$4:$A$11,0)),"") | C10: A3.1 | D10: =IFERROR(INDEX(Codebook!$B$4:$B$62,MATCH($C10,Codebook!$A$4:$A$62,0)),"") | E10: Seul. Pas de formation. Webinaire récent mais j'étais en mission. Testé, trifouillé. | H10: T1
A11: J1 | B11: =IFERROR(INDEX(Panel!$B$4:$B$11,MATCH($A11,Panel!$A$4:$A$11,0)),"") | C11: A3.1 | D11: =IFERROR(INDEX(Codebook!$B$4:$B$62,MATCH($C11,Codebook!$A$4:$A$62,0)),"") | E11: Suivi progrès : mars quasi rien, texte brut moche. Mai actions sans styling. Récemment diapos entières en un prompt. Changé en 3 mois. | H11: T1
A12: J1 | B12: =IFERROR(INDEX(Panel!$B$4:$B$11,MATCH($A12,Panel!$A$4:$A$11,0)),"") | C12: A4.1 | D12: =IFERROR(INDEX(Codebook!$B$4:$B$62,MATCH($C12,Codebook!$A$4:$A$62,0)),"") | E12: Propale, gagné 2h. Utilisées pour relire 3x le doc. Vérifier ancrage client. | F12: Propale | H12: T1
A13: J1 | B13: =IFERROR(INDEX(Panel!$B$4:$B$11,MATCH($A13,Panel!$A$4:$A$11,0)),"") | C13: A4.1 | D13: =IFERROR(INDEX(Codebook!$B$4:$B$62,MATCH($C13,Codebook!$A$4:$A$62,0)),"") | E13: Permet de passer + de temps sur qualité fond, moins forme/squelette. Contre-intuitif, mais fait mieux sur l'essentiel. | H13: T1
A14: J1 | B14: =IFERROR(INDEX(Panel!$B$4:$B$11,MATCH($A14,Panel!$A$4:$A$11,0)),"") | C14: D3.1 | D14: =IFERROR(INDEX(Codebook!$B$4:$B$62,MATCH($C14,Codebook!$A$4:$A$62,0)),"") | E14: Sujet hyper technique, règlementation bancaire. Texte vague, presque juste, refs à directives inexistantes. | H14: T1
A15: J1 | B15: =IFERROR(INDEX(Panel!$B$4:$B$11,MATCH($A15,Panel!$A$4:$A$11,0)),"") | C15: A4.3 | D15: =IFERROR(INDEX(Codebook!$B$4:$B$62,MATCH($C15,Codebook!$A$4:$A$62,0)),"") | E15: 20 min à reformuler prompts, rien. Réécrit 15 min. Depuis, trop pointu sans sources, je fais direct. | H15: T1
A16: J1 | B16: =IFERROR(INDEX(Panel!$B$4:$B$11,MATCH($A16,Panel!$A$4:$A$11,0)),"") | C16: A3.2 | D16: =IFERROR(INDEX(Codebook!$B$4:$B$62,MATCH($C16,Codebook!$A$4:$A$62,0)),"") | E16: Entre stagiaires/juniors, oui. Prompts, astuces. | H16: T1
A17: J1 | B17: =IFERROR(INDEX(Panel!$B$4:$B$11,MATCH($A17,Panel!$A$4:$A$11,0)),"") | C17: T3.1 | D17: =IFERROR(INDEX(Codebook!$B$4:$B$62,MATCH($C17,Codebook!$A$4:$A$62,0)),"") | E17: Avec seniors, plus discret. Pas dire « j'ai utilisé [l'outil] » au manager. Non-dit. Tout le monde l'utilise, personne le dit. Peur qu'on nous dise « tu réfléchis plus ». | H17: T1
A18: J1 | B18: =IFERROR(INDEX(Panel!$B$4:$B$11,MATCH($A18,Panel!$A$4:$A$11,0)),"") | C18: B2.2 | D18: =IFERROR(INDEX(Codebook!$B$4:$B$62,MATCH($C18,Codebook!$A$4:$A$62,0)),"") | E18: Différent. Notes/CR plus vite, mais pas sûr d'apprendre la même chose. | H18: T2
A19: J1 | B19: =IFERROR(INDEX(Panel!$B$4:$B$11,MATCH($A19,Panel!$A$4:$A$11,0)),"") | C19: B2.2 | D19: =IFERROR(INDEX(Codebook!$B$4:$B$62,MATCH($C19,Codebook!$A$4:$A$62,0)),"") | E19: Avant : trier, reformuler. Maintenant : colle notes, « structure-moi ». Gagne temps, mais n'exerce pas synthèse. Plus « relecteur » que « rédacteur ». | H19: T2
A20: J1 | B20: =IFERROR(INDEX(Panel!$B$4:$B$11,MATCH($A20,Panel!$A$4:$A$11,0)),"") | C20: B3.1 | D20: =IFERROR(INDEX(Codebook!$B$4:$B$62,MATCH($C20,Codebook!$A$4:$A$62,0)),"") | E20: Relecture manager. 1re propale, 2 j à faire. Manager a renvoyé plein de commentaires, titres, structure. Repris en comprenant pourquoi. | F20: Première propale | H20: T2
A21: J1 | B21: =IFERROR(INDEX(Panel!$B$4:$B$11,MATCH($A21,Panel!$A$4:$A$11,0)),"") | C21: B3.1 | D21: =IFERROR(INDEX(Codebook!$B$4:$B$62,MATCH($C21,Codebook!$A$4:$A$62,0)),"") | E21: Manager passe moins de temps sur forme, plus sur fond. Comms + intéressants (« raisonnement léger » vs « titres pas alignés »). Paradoxalement améliore relecture senior. | G21: Contredit l'hypothèse B3.2 | H21: T2
A22: J1 | B22: =IFERROR(INDEX(Panel!$B$4:$B$11,MATCH($A22,Panel!$A$4:$A$11,0)),"") | C22: B2.2 | D22: =IFERROR(INDEX(Codebook!$B$4:$B$62,MATCH($C22,Codebook!$A$4:$A$62,0)),"") | E22: Mais crainte : perdre capacité à faire version seule. | H22: T2
A23: J1 | B23: =IFERROR(INDEX(Panel!$B$4:$B$11,MATCH($A23,Panel!$A$4:$A$11,0)),"") | C23: D3.1 | D23: =IFERROR(INDEX(Codebook!$B$4:$B$62,MATCH($C23,Codebook!$A$4:$A$62,0)),"") | E23: Adaptation CV. Au début à la main, puis outil. Une fois, dérapage : IA inventé projets inexistants. Si pas vérifié ligne à ligne, mensonge pur. | F23: Adaptation de CV | H23: T2
A24: J1 | B24: =IFERROR(INDEX(Panel!$B$4:$B$11,MATCH($A24,Panel!$A$4:$A$11,0)),"") | C24: B2.3 | D24: =IFERROR(INDEX(Codebook!$B$4:$B$62,MATCH($C24,Codebook!$A$4:$A$62,0)),"") | E24: Depuis, plus confiance sur les faits. | H24: T2
A25: J1 | B25: =IFERROR(INDEX(Panel!$B$4:$B$11,MATCH($A25,Panel!$A$4:$A$11,0)),"") | C25: C1.3 | D25: =IFERROR(INDEX(Codebook!$B$4:$B$62,MATCH($C25,Codebook!$A$4:$A$62,0)),"") | E25: Parler leur langage (métier, contraintes). + Responsabilité : « ces gens-là ont vérifié, engagés ». | H25: T3
A26: J1 | B26: =IFERROR(INDEX(Panel!$B$4:$B$11,MATCH($A26,Panel!$A$4:$A$11,0)),"") | C26: C1.3 | D26: =IFERROR(INDEX(Codebook!$B$4:$B$62,MATCH($C26,Codebook!$A$4:$A$62,0)),"") | E26: Client ne demande pas IA, demande vrai. Confiance = nom sur le document. | H26: T3
A27: J1 | B27: =IFERROR(INDEX(Panel!$B$4:$B$11,MATCH($A27,Panel!$A$4:$A$11,0)),"") | C27: C2.2 | D27: =IFERROR(INDEX(Codebook!$B$4:$B$62,MATCH($C27,Codebook!$A$4:$A$62,0)),"") | E27: Non. Pas mentir si demande, mais pas mettre en avant. Risque : « pourquoi je paie un cabinet ? ». | H27: T3
A28: J1 | B28: =IFERROR(INDEX(Panel!$B$4:$B$11,MATCH($A28,Panel!$A$4:$A$11,0)),"") | C28: C2.2 | D28: =IFERROR(INDEX(Codebook!$B$4:$B$62,MATCH($C28,Codebook!$A$4:$A$62,0)),"") | E28: Clients soupçonnent. On élude « technologies qui aident ». Jamais dit « on génère des slides avec [l'outil] ». Sujet tabou. | H28: T3
A29: J1 | B29: =IFERROR(INDEX(Panel!$B$4:$B$11,MATCH($A29,Panel!$A$4:$A$11,0)),"") | C29: C1.1 | D29: =IFERROR(INDEX(Codebook!$B$4:$B$62,MATCH($C29,Codebook!$A$4:$A$62,0)),"") | E29: Erreurs factuelles. Chiffre faux => tout remis en cause. Erreur humaine excusable, erreur machine = faute pro. | H29: T3
A30: J1 | B30: =IFERROR(INDEX(Panel!$B$4:$B$11,MATCH($A30,Panel!$A$4:$A$11,0)),"") | C30: C3.1 | D30: =IFERROR(INDEX(Codebook!$B$4:$B$62,MATCH($C30,Codebook!$A$4:$A$62,0)),"") | E30: Capacité à prendre des risques. Dire vérité inconfortable. IA fait analyse/synthèse/mise en forme, pas prendre position. Payé pour jugement. | H30: T3
A31: J1 | B31: =IFERROR(INDEX(Panel!$B$4:$B$11,MATCH($A31,Panel!$A$4:$A$11,0)),"") | C31: D1.1 | D31: =IFERROR(INDEX(Codebook!$B$4:$B$62,MATCH($C31,Codebook!$A$4:$A$62,0)),"") | E31: Officiellement, oui. Session y a 2 mois. [Outil homologué] approuvé, attention données confidentielles, anonymiser. | H31: T4
A32: J1 | B32: =IFERROR(INDEX(Panel!$B$4:$B$11,MATCH($A32,Panel!$A$4:$A$11,0)),"") | C32: D1.3 | D32: =IFERROR(INDEX(Codebook!$B$4:$B$62,MATCH($C32,Codebook!$A$4:$A$62,0)),"") | E32: [Outils non officiels] = flou total. « Faites attention », pas de règle écrite. | H32: T4
A33: J1 | B33: =IFERROR(INDEX(Panel!$B$4:$B$11,MATCH($A33,Panel!$A$4:$A$11,0)),"") | C33: A4.4 | D33: =IFERROR(INDEX(Codebook!$B$4:$B$62,MATCH($C33,Codebook!$A$4:$A$62,0)),"") | E33: Utilise officieusement, très attention. Pas sûr que tout le monde prudent. | H33: T4
A34: J1 | B34: =IFERROR(INDEX(Panel!$B$4:$B$11,MATCH($A34,Panel!$A$4:$A$11,0)),"") | C34: D2.1 | D34: =IFERROR(INDEX(Codebook!$B$4:$B$62,MATCH($C34,Codebook!$A$4:$A$62,0)),"") | E34: Revue hiérarchique. Version préliminaire -> manager -> commentaires -> corrige -> valid. | H34: T4
A35: J1 | B35: =IFERROR(INDEX(Panel!$B$4:$B$11,MATCH($A35,Panel!$A$4:$A$11,0)),"") | C35: D2.3 | D35: =IFERROR(INDEX(Codebook!$B$4:$B$62,MATCH($C35,Codebook!$A$4:$A$62,0)),"") | E35: Pas de « check IA ». Personne demande « généré par ? ». Contrôle fond, pas processus. Managers soupçonnent mais ne posent pas. | H35: T4
A36: J1 | B36: =IFERROR(INDEX(Panel!$B$4:$B$11,MATCH($A36,Panel!$A$4:$A$11,0)),"") | C36: T3.1 | D36: =IFERROR(INDEX(Codebook!$B$4:$B$62,MATCH($C36,Codebook!$A$4:$A$62,0)),"") | E36: Dit à collègue stagiaire, rigolé. Pas dit manager. Honte. | F36: Quasi-incident CV | H36: T4
A37: J1 | B37: =IFERROR(INDEX(Panel!$B$4:$B$11,MATCH($A37,Panel!$A$4:$A$11,0)),"") | C37: D3.2 | D37: =IFERROR(INDEX(Codebook!$B$4:$B$62,MATCH($C37,Codebook!$A$4:$A$62,0)),"") | E37: Frayeur. Si parti sans vérifier, mensonge client. Responsabilité sur moi. | F37: Quasi-incident CV | H37: T4
A38: J1 | B38: =IFERROR(INDEX(Panel!$B$4:$B$11,MATCH($A38,Panel!$A$4:$A$11,0)),"") | C38: T2.2 | D38: =IFERROR(INDEX(Codebook!$B$4:$B$62,MATCH($C38,Codebook!$A$4:$A$62,0)),"") | E38: « Utiliser IA pour rédactionnel/structure/synthèse. Mais justifier chaque fait. Si pas justifiable, pas utiliser. » | H38: T4
A39: J1 | B39: =IFERROR(INDEX(Panel!$B$4:$B$11,MATCH($A39,Panel!$A$4:$A$11,0)),"") | C39: D2.2 | D39: =IFERROR(INDEX(Codebook!$B$4:$B$62,MATCH($C39,Codebook!$A$4:$A$62,0)),"") | E39: Ce qui m'a sauvé = avoir gardé source de vérité à côté. | H39: T4
A40: J1 | B40: =IFERROR(INDEX(Panel!$B$4:$B$11,MATCH($A40,Panel!$A$4:$A$11,0)),"") | C40: D5.2 | D40: =IFERROR(INDEX(Codebook!$B$4:$B$62,MATCH($C40,Codebook!$A$4:$A$62,0)),"") | E40: Clarifier statut outils non-officiels. Interdire ou approuver avec garde-fous. Flou dangereux. | H40: T5
A41: J1 | B41: =IFERROR(INDEX(Panel!$B$4:$B$11,MATCH($A41,Panel!$A$4:$A$11,0)),"") | C41: T2.2 | D41: =IFERROR(INDEX(Codebook!$B$4:$B$62,MATCH($C41,Codebook!$A$4:$A$62,0)),"") | E41: Formation obligatoire pas sur prompts, mais sur détection hallucinations. Risque = consultants ne voient pas erreurs. | H41: T5
A42: J1 | B42: =IFERROR(INDEX(Panel!$B$4:$B$11,MATCH($A42,Panel!$A$4:$A$11,0)),"") | C42: B2.2 | D42: =IFERROR(INDEX(Codebook!$B$4:$B$62,MATCH($C42,Codebook!$A$4:$A$62,0)),"") | E42: Slide en 30 sec => moins enclin à réfléchir fond avant. Plus vite, mais impression de ne pas maîtriser sujet. Illusion de compétence. | H42: T5
A43: J1 | B43: =IFERROR(INDEX(Panel!$B$4:$B$11,MATCH($A43,Panel!$A$4:$A$11,0)),"") | C43: B4.1 | D43: =IFERROR(INDEX(Codebook!$B$4:$B$62,MATCH($C43,Codebook!$A$4:$A$62,0)),"") | E43: Dans 6 mois, saurai faire structure seul ? | H43: T5
A44: J2 | B44: =IFERROR(INDEX(Panel!$B$4:$B$11,MATCH($A44,Panel!$A$4:$A$11,0)),"") | C44: A1.3 | D44: =IFERROR(INDEX(Codebook!$B$4:$B$62,MATCH($C44,Codebook!$A$4:$A$62,0)),"") | E44: Propale. 3 jours pour répondre. Section « leviers d'innovation ». Fils contexte 2 phrases. Demandé 5 pistes d'injects innovants. | F44: Appel d'offre | G44: A1.5 ? | H44: T1
A45: J2 | B45: =IFERROR(INDEX(Panel!$B$4:$B$11,MATCH($A45,Panel!$A$4:$A$11,0)),"") | C45: A4.1 | D45: =IFERROR(INDEX(Codebook!$B$4:$B$62,MATCH($C45,Codebook!$A$4:$A$62,0)),"") | E45: Sorti « panne coms », « fuite presse ». Certaines utilisables, d'autres trop génériques. Gardé 3. Adapté formulations. | G45: B2.3 ? | H45: T1
A46: J2 | B46: =IFERROR(INDEX(Panel!$B$4:$B$11,MATCH($A46,Panel!$A$4:$A$11,0)),"") | C46: A1.3 | D46: =IFERROR(INDEX(Codebook!$B$4:$B$62,MATCH($C46,Codebook!$A$4:$A$62,0)),"") | E46: Propales. Injects. Créatif : scénarios, rebondissements, données fictives crédibles. | H46: T1
A47: J2 | B47: =IFERROR(INDEX(Panel!$B$4:$B$11,MATCH($A47,Panel!$A$4:$A$11,0)),"") | C47: A2.2 | D47: =IFERROR(INDEX(Codebook!$B$4:$B$62,MATCH($C47,Codebook!$A$4:$A$62,0)),"") | E47: Jamais sur analyse post-exercice. Chiffrage, REX concrets. L'IA n'était pas dans la salle. Fais main. | F47: Exercice de crise | H47: T1
A48: J2 | B48: =IFERROR(INDEX(Panel!$B$4:$B$11,MATCH($A48,Panel!$A$4:$A$11,0)),"") | C48: A3.1 | D48: =IFERROR(INDEX(Codebook!$B$4:$B$62,MATCH($C48,Codebook!$A$4:$A$62,0)),"") | E48: Sur le tas. Pas de formation. Intuitif. Tu demandes, il répond. Pas de prompts avancés. | H48: T1
A49: J2 | B49: =IFERROR(INDEX(Panel!$B$4:$B$11,MATCH($A49,Panel!$A$4:$A$11,0)),"") | C49: A4.1 | D49: =IFERROR(INDEX(Codebook!$B$4:$B$62,MATCH($C49,Codebook!$A$4:$A$62,0)),"") | E49: Gagné 1h sur recherche d'idées. Utilisée pour affiner structure, vérifier arguments. Passé + temps sur cohérence globale. | H49: T1
A50: J2 | B50: =IFERROR(INDEX(Panel!$B$4:$B$11,MATCH($A50,Panel!$A$4:$A$11,0)),"") | C50: A4.3 | D50: =IFERROR(INDEX(Codebook!$B$4:$B$62,MATCH($C50,Codebook!$A$4:$A$62,0)),"") | E50: Injects cyber hyper spécifique. Trop générique. 10 min à reformuler prompt, exemples. Rien. Réécrit en 5 min. Trop spécifique = tête. | G50: A4.2 ? | H50: T1
A51: J2 | B51: =IFERROR(INDEX(Panel!$B$4:$B$11,MATCH($A51,Panel!$A$4:$A$11,0)),"") | C51: A3.2 | D51: =IFERROR(INDEX(Codebook!$B$4:$B$62,MATCH($C51,Codebook!$A$4:$A$62,0)),"") | E51: Un peu. Astuces. Informel. Pas en réunion ou avec managers. | G51: T3.1 ? | H51: T1
A52: J2 | B52: =IFERROR(INDEX(Panel!$B$4:$B$11,MATCH($A52,Panel!$A$4:$A$11,0)),"") | C52: T3.1 | D52: =IFERROR(INDEX(Codebook!$B$4:$B$62,MATCH($C52,Codebook!$A$4:$A$62,0)),"") | E52: Tout le monde l'utilise, personne en parle. Secret de polichinelle. | H52: T1
A53: J2 | B53: =IFERROR(INDEX(Panel!$B$4:$B$11,MATCH($A53,Panel!$A$4:$A$11,0)),"") | C53: B3.3 | D53: =IFERROR(INDEX(Codebook!$B$4:$B$62,MATCH($C53,Codebook!$A$4:$A$62,0)),"") | E53: Pratique. Propales, exos, restitutions. IA aide à aller vite, mais n'apprend pas le métier. | G53: B1.1 ? | H53: T2
A54: J2 | B54: =IFERROR(INDEX(Panel!$B$4:$B$11,MATCH($A54,Panel!$A$4:$A$11,0)),"") | C54: B3.3 | D54: =IFERROR(INDEX(Codebook!$B$4:$B$62,MATCH($C54,Codebook!$A$4:$A$62,0)),"") | E54: Clients, seniors, analyse terrain. Outil, pas mentor. | H54: T2
A55: J2 | B55: =IFERROR(INDEX(Panel!$B$4:$B$11,MATCH($A55,Panel!$A$4:$A$11,0)),"") | C55: A2.3 | D55: =IFERROR(INDEX(Codebook!$B$4:$B$62,MATCH($C55,Codebook!$A$4:$A$62,0)),"") | E55: Incertitude. Propale, tu sais pas ce que client attend. Exo, paramètres changent. Adaptation. | G55: AUCUN | H55: T2
A56: J2 | B56: =IFERROR(INDEX(Panel!$B$4:$B$11,MATCH($A56,Panel!$A$4:$A$11,0)),"") | C56: B1.2 | D56: =IFERROR(INDEX(Codebook!$B$4:$B$62,MATCH($C56,Codebook!$A$4:$A$62,0)),"") | E56: Répétitives = rien. IA fait bien. Cœur = décision sous pression. IA le fait pas. | H56: T2
A57: J2 | B57: =IFERROR(INDEX(Panel!$B$4:$B$11,MATCH($A57,Panel!$A$4:$A$11,0)),"") | C57: B2.1 | D57: =IFERROR(INDEX(Codebook!$B$4:$B$62,MATCH($C57,Codebook!$A$4:$A$62,0)),"") | E57: Injects = créatif. IA partenaire brainstorming. Gagne temps sur génération. Consacre sur affinage/crédibilité. Pas appauvrit, rend + efficace. Mais garde la main. | G57: A4.1 ? | H57: T2
A58: J2 | B58: =IFERROR(INDEX(Panel!$B$4:$B$11,MATCH($A58,Panel!$A$4:$A$11,0)),"") | C58: B2.3 | D58: =IFERROR(INDEX(Codebook!$B$4:$B$62,MATCH($C58,Codebook!$A$4:$A$62,0)),"") | E58: Cohérence globale. Crédibilité dans contexte client. Si incohérences ou trop générique, écarte ou retravaille. | H58: T2
A59: J2 | B59: =IFERROR(INDEX(Panel!$B$4:$B$11,MATCH($A59,Panel!$A$4:$A$11,0)),"") | C59: D2.3 | D59: =IFERROR(INDEX(Codebook!$B$4:$B$62,MATCH($C59,Codebook!$A$4:$A$62,0)),"") | E59: Pas vérifier sources/chiffres. Pas factuel. Créativité/structure. | G59: B2.3 ? | H59: T2
A60: J2 | B60: =IFERROR(INDEX(Panel!$B$4:$B$11,MATCH($A60,Panel!$A$4:$A$11,0)),"") | C60: C1.1 | D60: =IFERROR(INDEX(Codebook!$B$4:$B$62,MATCH($C60,Codebook!$A$4:$A$62,0)),"") | E60: Anticiper. Scénarios, imprévus, conséquences. Plan solide + adaptation en direct = confiance. | G60: C1.2 ? | H60: T3
A61: J2 | B61: =IFERROR(INDEX(Panel!$B$4:$B$11,MATCH($A61,Panel!$A$4:$A$11,0)),"") | C61: A2.3 | D61: =IFERROR(INDEX(Codebook!$B$4:$B$62,MATCH($C61,Codebook!$A$4:$A$62,0)),"") | E61: IA prépare, jour J consultant terrain. | G61: C3.1 ? | H61: T3
A62: J2 | B62: =IFERROR(INDEX(Panel!$B$4:$B$11,MATCH($A62,Panel!$A$4:$A$11,0)),"") | C62: C2.2 | D62: =IFERROR(INDEX(Codebook!$B$4:$B$62,MATCH($C62,Codebook!$A$4:$A$62,0)),"") | E62: Non. N'apporte rien. Client veut livrable de qualité. Peu importe comment. | G62: C1.2 ? | H62: T3
A63: J2 | B63: =IFERROR(INDEX(Panel!$B$4:$B$11,MATCH($A63,Panel!$A$4:$A$11,0)),"") | C63: C2.2 | D63: =IFERROR(INDEX(Codebook!$B$4:$B$62,MATCH($C63,Codebook!$A$4:$A$62,0)),"") | E63: Si dis « utilisé [l'outil] », distraction. « C'est vraiment vous ? ». Pas mentionner. | H63: T3
A64: J2 | B64: =IFERROR(INDEX(Panel!$B$4:$B$11,MATCH($A64,Panel!$A$4:$A$11,0)),"") | C64: C1.1 | D64: =IFERROR(INDEX(Codebook!$B$4:$B$62,MATCH($C64,Codebook!$A$4:$A$62,0)),"") | E64: Ancrage. Si client sent pas compris secteur, contraintes, culture, doute. IA générique, pas nuances contexte. Livrable juste mais pas pertinent. | H64: T3
A65: J2 | B65: =IFERROR(INDEX(Panel!$B$4:$B$11,MATCH($A65,Panel!$A$4:$A$11,0)),"") | C65: C3.1 | D65: =IFERROR(INDEX(Codebook!$B$4:$B$62,MATCH($C65,Codebook!$A$4:$A$62,0)),"") | E65: Expérience humaine. Crise = relationnel, improvisation, prise de risque. Conseil = présence, pas algorithmes. | G65: C1.1 ? | H65: T3
A66: J2 | B66: =IFERROR(INDEX(Panel!$B$4:$B$11,MATCH($A66,Panel!$A$4:$A$11,0)),"") | C66: D1.1 | D66: =IFERROR(INDEX(Codebook!$B$4:$B$62,MATCH($C66,Codebook!$A$4:$A$62,0)),"") | E66: [Outil homologué] officiel. Communication générale. Rien contraignant. | G66: D1.3 ? | H66: T4
A67: J2 | B67: =IFERROR(INDEX(Panel!$B$4:$B$11,MATCH($A67,Panel!$A$4:$A$11,0)),"") | C67: D3.3 | D67: =IFERROR(INDEX(Codebook!$B$4:$B$62,MATCH($C67,Codebook!$A$4:$A$62,0)),"") | E67: Passé armée => sensibilisé confi. Pas besoin qu'on dise. Je fais nature. | G67: D1.2 ? | H67: T4
A68: J2 | B68: =IFERROR(INDEX(Panel!$B$4:$B$11,MATCH($A68,Panel!$A$4:$A$11,0)),"") | C68: D2.1 | D68: =IFERROR(INDEX(Codebook!$B$4:$B$62,MATCH($C68,Codebook!$A$4:$A$62,0)),"") | E68: Relecture manager/senior. Cohérence, chiffres, reco. Pas demandent si IA. S'en doutent peut-être. Contenu bon, processus pas regardé. | G68: D2.3 ? | H68: T4
A69: J2 | B69: =IFERROR(INDEX(Panel!$B$4:$B$11,MATCH($A69,Panel!$A$4:$A$11,0)),"") | C69: A4.1 | D69: =IFERROR(INDEX(Codebook!$B$4:$B$62,MATCH($C69,Codebook!$A$4:$A$62,0)),"") | E69: Pas vraiment. Trop générique, mais pas inventé. Utilise pour idées, pas faits. Risque limité. | G69: AUCUN | H69: T4
A70: J2 | B70: =IFERROR(INDEX(Panel!$B$4:$B$11,MATCH($A70,Panel!$A$4:$A$11,0)),"") | C70: D3.1 | D70: =IFERROR(INDEX(Codebook!$B$4:$B$62,MATCH($C70,Codebook!$A$4:$A$62,0)),"") | E70: Collègues [outils non officiels] données = chiffres nulle part. Ont dû reprendre. Je préfère éviter. | G70: A4.4 ? | H70: T4
A71: J2 | B71: =IFERROR(INDEX(Panel!$B$4:$B$11,MATCH($A71,Panel!$A$4:$A$11,0)),"") | C71: T2.2 | D71: =IFERROR(INDEX(Codebook!$B$4:$B$62,MATCH($C71,Codebook!$A$4:$A$62,0)),"") | E71: « Aide créativité/structure, pas substitut jugement. » Vérification : si faits, justifiables. Données sensibles : pas outils non-officiels. | G71: D5.2 ? | H71: T4
A72: J2 | B72: =IFERROR(INDEX(Panel!$B$4:$B$11,MATCH($A72,Panel!$A$4:$A$11,0)),"") | C72: D5.2 | D72: =IFERROR(INDEX(Codebook!$B$4:$B$62,MATCH($C72,Codebook!$A$4:$A$62,0)),"") | E72: Charte simple. 1 page. 3 règles : possible, impossible, vérifier. | G72: T2.2 ? | H72: T5
A73: J2 | B73: =IFERROR(INDEX(Panel!$B$4:$B$11,MATCH($A73,Panel!$A$4:$A$11,0)),"") | C73: T2.2 | D73: =IFERROR(INDEX(Codebook!$B$4:$B$62,MATCH($C73,Codebook!$A$4:$A$62,0)),"") | E73: Canal [messagerie interne] bonnes pratiques. Actuellement on tâtonne. Certains font erreurs évitables. | G73: A3.2 ? | H73: T5
A74: J2 | B74: =IFERROR(INDEX(Panel!$B$4:$B$11,MATCH($A74,Panel!$A$4:$A$11,0)),"") | C74: T1.1 | D74: =IFERROR(INDEX(Codebook!$B$4:$B$62,MATCH($C74,Codebook!$A$4:$A$62,0)),"") | E74: Culture cabinet. Ici ouvert, mais ambivalence. On dit innover, pas dit comment intégrer. Décalage discours/pratique. | G74: D1.3 ? | H74: T5
A75: E1 | B75: =IFERROR(INDEX(Panel!$B$4:$B$11,MATCH($A75,Panel!$A$4:$A$11,0)),"") | C75: D2.1 | D75: =IFERROR(INDEX(Codebook!$B$4:$B$62,MATCH($C75,Codebook!$A$4:$A$62,0)),"") | E75: À mon niveau, passe + temps à relire qu'à écrire. | G75: B3.1 ? | H75: T0
A76: E1 | B76: =IFERROR(INDEX(Panel!$B$4:$B$11,MATCH($A76,Panel!$A$4:$A$11,0)),"") | C76: A3.2 | D76: =IFERROR(INDEX(Codebook!$B$4:$B$62,MATCH($C76,Codebook!$A$4:$A$62,0)),"") | E76: 2-3 semaines. Curiosité. Junior parlait d'un prompt pour notes réunion. Testé sur CR que j'avais fait. Résultat correct, mais pas + que ce que j'avais. | G76: A4.1 ? | H76: T1
... A78: E1 | B78: =IFERROR(INDEX(Panel!$B$4:$B$11,MATCH($A78,Panel!$A$4:$A$11,0)),"") | C78: A4.3 | D78: =IFERROR(INDEX(Codebook!$B$4:$B$62,MATCH($C78,Codebook!$A$4:$A$62,0)),"") | E78: Pas vraiment quotidien. De temps en temps. Sujets moins maîtrisés. Rare. | G78: A1.3 ? | H78: T1
A79: E1 | B79: =IFERROR(INDEX(Panel!$B$4:$B$11,MATCH($A79,Panel!$A$4:$A$11,0)),"") | C79: A4.3 | D79: =IFERROR(INDEX(Codebook!$B$4:$B$62,MATCH($C79,Codebook!$A$4:$A$62,0)),"") | E79: Préfère méthodes : templates, bases données anciens livrables, connaissance clients. IA apporte pas grand-chose. | H79: T1
A80: E1 | B80: =IFERROR(INDEX(Panel!$B$4:$B$11,MATCH($A80,Panel!$A$4:$A$11,0)),"") | C80: T1.2 | D80: =IFERROR(INDEX(Codebook!$B$4:$B$62,MATCH($C80,Codebook!$A$4:$A$62,0)),"") | E80: Juniors l'utilisent tout le temps. Eux ont besoin de béquille. | G80: B4.1 ? | H80: T1
A81: E1 | B81: =IFERROR(INDEX(Panel!$B$4:$B$11,MATCH($A81,Panel!$A$4:$A$11,0)),"") | C81: A3.3 | D81: =IFERROR(INDEX(Codebook!$B$4:$B$62,MATCH($C81,Codebook!$A$4:$A$62,0)),"") | E81: Session sensibilisation y a qqs mois. Pas creusé. Pas de bloc-notes prompts, pas veille. | G81: A4.3 ? | H81: T1
A82: E1 | B82: =IFERROR(INDEX(Panel!$B$4:$B$11,MATCH($A82,Panel!$A$4:$A$11,0)),"") | C82: A4.1 | D82: =IFERROR(INDEX(Codebook!$B$4:$B$62,MATCH($C82,Codebook!$A$4:$A$62,0)),"") | E82: Gain de temps à mettre sur relecture/vérification. Ce qui sort IA demande contrôle. Au final, est-ce qu'on gagne vraiment du temps ? Pas sûr. | G82: B2.3 ? | H82: T1
A83: E1 | B83: =IFERROR(INDEX(Panel!$B$4:$B$11,MATCH($A83,Panel!$A$4:$A$11,0)),"") | C83: D3.1 | D83: =IFERROR(INDEX(Codebook!$B$4:$B$62,MATCH($C83,Codebook!$A$4:$A$62,0)),"") | E83: Livrable client important. Junior avait utilisé IA sur tout. Incohérences partout. Chiffres faux. Réfs à textes inexistants. Formulations justes mais sens trahi. | F83: Incident livrable client | G83: D3.2 ? | H83: T1
A84: E1 | B84: =IFERROR(INDEX(Panel!$B$4:$B$11,MATCH($A84,Panel!$A$4:$A$11,0)),"") | C84: D3.2 | D84: =IFERROR(INDEX(Codebook!$B$4:$B$62,MATCH($C84,Codebook!$A$4:$A$62,0)),"") | E84: Refait tout en catastrophe, avec junior, une nuit. Passé + temps corriger IA que produire nous-mêmes. | F84: Incident livrable client | G84: A4.1 ? | H84: T1
A85: E1 | B85: =IFERROR(INDEX(Panel!$B$4:$B$11,MATCH($A85,Panel!$A$4:$A$11,0)),"") | C85: T3.2 | D85: =IFERROR(INDEX(Codebook!$B$4:$B$62,MATCH($C85,Codebook!$A$4:$A$62,0)),"") | E85: Depuis, très prudent. Demande systématiquement : « qu'est-ce qui est de toi, qu'est-ce qui est de l'IA ? » | H85: T1
A86: E1 | B86: =IFERROR(INDEX(Panel!$B$4:$B$11,MATCH($A86,Panel!$A$4:$A$11,0)),"") | C86: A3.2 | D86: =IFERROR(INDEX(Codebook!$B$4:$B$62,MATCH($C86,Codebook!$A$4:$A$62,0)),"") | E86: Entre managers, oui. On partage. Consensus : IA là, faut composer, œil critique. Tous eu histoires livrables problématiques. | H86: T1
A87: E1 | B87: =IFERROR(INDEX(Panel!$B$4:$B$11,MATCH($A87,Panel!$A$4:$A$11,0)),"") | C87: B2.3 | D87: =IFERROR(INDEX(Codebook!$B$4:$B$62,MATCH($C87,Codebook!$A$4:$A$62,0)),"") | E87: À mon niveau, changement métier. Vérifie plus seulement fond/forme. Vérifie aussi ce que IA a apporté. Compétence nouvelle à développer. | H87: T1
A88: E1 | B88: =IFERROR(INDEX(Panel!$B$4:$B$11,MATCH($A88,Panel!$A$4:$A$11,0)),"") | C88: B3.1 | D88: =IFERROR(INDEX(Codebook!$B$4:$B$62,MATCH($C88,Codebook!$A$4:$A$62,0)),"") | E88: Quand j'ai commencé : faisait, se trompait, se faisait reprendre. | G88: B3.3 ? | H88: T2
A89: E1 | B89: =IFERROR(INDEX(Panel!$B$4:$B$11,MATCH($A89,Panel!$A$4:$A$11,0)),"") | C89: B2.2 | D89: =IFERROR(INDEX(Codebook!$B$4:$B$62,MATCH($C89,Codebook!$A$4:$A$62,0)),"") | E89: Aujourd'hui juniors arrivent avec livrables très propres très vite. Mais profondeur ? IA donne première version, retravaillent, mais pas chemin réflexion initiale. | H89: T2
A90: E1 | B90: =IFERROR(INDEX(Panel!$B$4:$B$11,MATCH($A90,Panel!$A$4:$A$11,0)),"") | C90: B2.2 | D90: =IFERROR(INDEX(Codebook!$B$4:$B$62,MATCH($C90,Codebook!$A$4:$A$62,0)),"") | E90: Jeunes très bons forme, mais mal justifier fond. Apprentissage différent. Pas sûr meilleur. | G90: B4.2 ? | H90: T2
A91: E1 | B91: =IFERROR(INDEX(Panel!$B$4:$B$11,MATCH($A91,Panel!$A$4:$A$11,0)),"") | C91: A2.2 | D91: =IFERROR(INDEX(Codebook!$B$4:$B$62,MATCH($C91,Codebook!$A$4:$A$62,0)),"") | E91: Choix difficiles. Décider reco, orientation stratégique, pertinence client. IA peut pas. | G91: C3.1 ? | H91: T2
A92: E1 | B92: =IFERROR(INDEX(Panel!$B$4:$B$11,MATCH($A92,Panel!$A$4:$A$11,0)),"") | C92: B1.2 | D92: =IFERROR(INDEX(Codebook!$B$4:$B$62,MATCH($C92,Codebook!$A$4:$A$62,0)),"") | E92: Répétitives, rédaction, mise en forme : IA peut aider. Permet juniors passer + temps sur valeur ajoutée. | G92: B2.1 ? | H92: T2
A93: E1 | B93: =IFERROR(INDEX(Panel!$B$4:$B$11,MATCH($A93,Panel!$A$4:$A$11,0)),"") | C93: B1.1 | D93: =IFERROR(INDEX(Codebook!$B$4:$B$62,MATCH($C93,Codebook!$A$4:$A$62,0)),"") | E93: Mais faut qu'ils aient fait tâches ingrates au moins 1-2x à la main. Pour comprendre. Sans, sauront pas juger ce que IA sort. | H93: T2
A94: E1 | B94: =IFERROR(INDEX(Panel!$B$4:$B$11,MATCH($A94,Panel!$A$4:$A$11,0)),"") | C94: D2.1 | D94: =IFERROR(INDEX(Codebook!$B$4:$B$62,MATCH($C94,Codebook!$A$4:$A$62,0)),"") | E94: Plus seulement contenu final. Processus. Demande : « comment arrivé ? Qu'est-ce fait toi ? Qu'est-ce IA ? Vérifié sources ? » | G94: T3.2 ? | H94: T2
A95: E1 | B95: =IFERROR(INDEX(Panel!$B$4:$B$11,MATCH($A95,Panel!$A$4:$A$11,0)),"") | C95: B2.3 | D95: =IFERROR(INDEX(Codebook!$B$4:$B$62,MATCH($C95,Codebook!$A$4:$A$62,0)),"") | E95: Devenu partie importante rôle manager : former juniors à vérification critique. | G95: B3.1 ? | H95: T2
A96: E1 | B96: =IFERROR(INDEX(Panel!$B$4:$B$11,MATCH($A96,Panel!$A$4:$A$11,0)),"") | C96: B3.1 | D96: =IFERROR(INDEX(Codebook!$B$4:$B$62,MATCH($C96,Codebook!$A$4:$A$62,0)),"") | E96: Jugement. Pourquoi telle formulation meilleure ? Pourquoi reco pertinente ? Pourquoi chiffre suspect ? Relecture = transmission compétences, pas correction technique. | H96: T2
A97: E1 | B97: =IFERROR(INDEX(Panel!$B$4:$B$11,MATCH($A97,Panel!$A$4:$A$11,0)),"") | C97: B3.3 | D97: =IFERROR(INDEX(Codebook!$B$4:$B$62,MATCH($C97,Codebook!$A$4:$A$62,0)),"") | E97: Avec IA, transmission + importante. Juniors peuvent illusion outil fait travail. Mon rôle = montrer que non. | G97: Contredit l'hypothèse B3.2 — B3.1 ? | H97: T2
A98: E1 | B98: =IFERROR(INDEX(Panel!$B$4:$B$11,MATCH($A98,Panel!$A$4:$A$11,0)),"") | C98: C1.3 | D98: =IFERROR(INDEX(Codebook!$B$4:$B$62,MATCH($C98,Codebook!$A$4:$A$62,0)),"") | E98: Solidité. Banque/assurance, pas approximatif. Client doit sentir vérifié, solide, pris responsabilités. | G98: C1.1 ? | H98: T3
A99: E1 | B99: =IFERROR(INDEX(Panel!$B$4:$B$11,MATCH($A99,Panel!$A$4:$A$11,0)),"") | C99: C2.3 | D99: =IFERROR(INDEX(Codebook!$B$4:$B$62,MATCH($C99,Codebook!$A$4:$A$62,0)),"") | E99: Oui. Clients demandent si on utilise IA. Répond : technologies aide décision, mais analyse finale/recommandations entièrement équipes. | H99: T3
A100: E1 | B100: =IFERROR(INDEX(Panel!$B$4:$B$11,MATCH($A100,Panel!$A$4:$A$11,0)),"") | C100: C2.2 | D100: =IFERROR(INDEX(Codebook!$B$4:$B$62,MATCH($C100,Codebook!$A$4:$A$62,0)),"") | E100: C'est vrai. Mais jamais « on génère slides avec [l'outil] ». Mal perçu. Client se demanderait ce qu'il paie. | H100: T3
A101: E1 | B101: =IFERROR(INDEX(Panel!$B$4:$B$11,MATCH($A101,Panel!$A$4:$A$11,0)),"") | C101: C2.2 | D101: =IFERROR(INDEX(Codebook!$B$4:$B$62,MATCH($C101,Codebook!$A$4:$A$62,0)),"") | E101: Non. Contre-productif. Client paie résultat, pas processus. Si mauvais, pas cacher derrière IA. Responsabilité sur nous. | G101: C3.2 ? | H101: T3
A102: E1 | B102: =IFERROR(INDEX(Panel!$B$4:$B$11,MATCH($A102,Panel!$A$4:$A$11,0)),"") | C102: C1.1 | D102: =IFERROR(INDEX(Codebook!$B$4:$B$62,MATCH($C102,Codebook!$A$4:$A$62,0)),"") | E102: Erreurs factuelles. Junior IA sans vérifier, coquilles grossières. Client pas dit direct, mais méfiance après. Mission suivante a demandé autre consultant. | F102: Conséquence commerciale | G102: D3.1 ? | H102: T3
...

Sheet Matrice
A1: Matrice codes x repondants (occurrences)
A2: Calcule automatiquement depuis l'onglet Verbatims. Ne rien saisir ici.
A4: Code | B4: Intitule | C4: J1 | D4: J2 | E4: J3 | F4: J4 | G4: E1 | H4: E2 | I4: E3 | J4: E4 | K4: Total | L4: Nb repondants
A5: A1.1 | B5: Recherche et veille | C5: =COUNTIFS(Verbatims!$A$5:$A$407,C$4,Verbatims!$C$5:$C$407,$A5) | D5: =COUNTIFS(Verbatims!$A$5:$A$407,D$4,Verbatims!$C$5:$C$407,$A5) | E5: =COUNTIFS(Verbatims!$A$5:$A$407,E$4,Verbatims!$C$5:$C$407,$A5) | F5: =COUNTIFS(Verbatims!$A$5:$A$407,F$4,Verbatims!$C$5:$C$407,$A5) | G5: =COUNTIFS(Verbatims!$A$5:$A$407,G$4,Verbatims!$C$5:$C$407,$A5) | H5: =COUNTIFS(Verbatims!$A$5:$A$407,H$4,Verbatims!$C$5:$C$407,$A5) | I5: =COUNTIFS(Verbatims!$A$5:$A$407,I$4,Verbatims!$C$5:$C$407,$A5) | J5: =COUNTIFS(Verbatims!$A$5:$A$407,J$4,Verbatims!$C$5:$C$407,$A5) | K5: =SUM(C5:J5) | L5: =COUNTIF(C5:J5,">0")
A6: A1.2 | B6: Synthese et reformulation | C6: =COUNTIFS(Verbatims!$A$5:$A$407,C$4,Verbatims!$C$5:$C$407,$A6) | D6: =COUNTIFS(Verbatims!$A$5:$A$407,D$4,Verbatims!$C$5:$C$407,$A6) | E6: =COUNTIFS(Verbatims!$A$5:$A$407,E$4,Verbatims!$C$5:$C$407,$A6) | F6: =COUNTIFS(Verbatims!$A$5:$A$407,F$4,Verbatims!$C$5:$C$407,$A6) | G6: =COUNTIFS(Verbatims!$A$5:$A$407,G$4,Verbatims!$C$5:$C$407,$A6) | H6: =COUNTIFS(Verbatims!$A$5:$A$407,H$4,Verbatims!$C$5:$C$407,$A6) | I6: =COUNTIFS(Verbatims!$A$5:$A$407,I$4,Verbatims!$C$5:$C$407,$A6) | J6: =COUNTIFS(Verbatims!$A$5:$A$407,J$4,Verbatims!$C$5:$C$407,$A6) | K6: =SUM(C6:J6) | L6: =COUNTIF(C6:J6,">0")
A7: A1.3 | B7: Premiere redaction | C7: =COUNTIFS(Verbatims!$A$5:$A$407,C$4,Verbatims!$C$5:$C$407,$A7) | D7: =COUNTIFS(Verbatims!$A$5:$A$407,D$4,Verbatims!$C$5:$C$407,$A7) | E7: =COUNTIFS(Verbatims!$A$5:$A$407,E$4,Verbatims!$C$5:$C$407,$A7) | F7: =COUNTIFS(Verbatims!$A$5:$A$407,F$4,Verbatims!$C$5:$C$407,$A7) | G7: =COUNTIFS(Verbatims!$A$5:$A$407,G$4,Verbatims!$C$5:$C$407,$A7) | H7: =COUNTIFS(Verbatims!$A$5:$A$407,H$4,Verbatims!$C$5:$C$407,$A7) | I7: =COUNTIFS(Verbatims!$A$5:$A$407,I$4,Verbatims!$C$5:$C$407,$A7) | J7: =COUNTIFS(Verbatims!$A$5:$A$407,J$4,Verbatims!$C$5:$C$407,$A7) | K7: =SUM(C7:J7) | L7: =COUNTIF(C7:J7,">0")
A8: A1.4 | B8: Traduction et mise en forme | C8: =COUNTIFS(Verbatims!$A$5:$A$407,C$4,Verbatims!$C$5:$C$407,$A8) | D8: =COUNTIFS(Verbatims!$A$5:$A$407,D$4,Verbatims!$C$5:$C$407,$A8) | E8: =COUNTIFS(Verbatims!$A$5:$A$407,E$4,Verbatims!$C$5:$C$407,$A8) | F8: =COUNTIFS(Verbatims!$A$5:$A$407,F$4,Verbatims!$C$5:$C$407,$A8) | G8: =COUNTIFS(Verbatims!$A$5:$A$407,G$4,Verbatims!$C$5:$C$407,$A8) | H8: =COUNTIFS(Verbatims!$A$5:$A$407,H$4,Verbatims!$C$5:$C$407,$A8) | I8: =COUNTIFS(Verbatims!$A$5:$A$407,I$4,Verbatims!$C$5:$C$407,$A8) | J8: =COUNTIFS(Verbatims!$A$5:$A$407,J$4,Verbatims!$C$5:$C$407,$A8) | K8: =SUM(C8:J8) | L8: =COUNTIF(C8:J8,">0")
A9: A1.5 | B9: Structuration du raisonnement | C9: =COUNTIFS(Verbatims!$A$5:$A$407,C$4,Verbatims!$C$5:$C$407,$A9) | D9: =COUNTIFS(Verbatims!$A$5:$A$407,D$4,Verbatims!$C$5:$C$407,$A9) | E9: =COUNTIFS(Verbatims!$A$5:$A$407,E$4,Verbatims!$C$5:$C$407,$A9) | F9: =COUNTIFS(Verbatims!$A$5:$A$407,F$4,Verbatims!$C$5:$C$407,$A9) | G9: =COUNTIFS(Verbatims!$A$5:$A$407,G$4,Verbatims!$C$5:$C$407,$A9) | H9: =COUNTIFS(Verbatims!$A$5:$A$407,H$4,Verbatims!$C$5:$C$407,$A9) | I9: =COUNTIFS(Verbatims!$A$5:$A$407,I$4,Verbatims!$C$5:$C$407,$A9) | J9: =COUNTIFS(Verbatims!$A$5:$A$407,J$4,Verbatims!$C$5:$C$407,$A9) | K9: =SUM(C9:J9) | L9: =COUNTIF(C9:J9,">0")
A10: A2.1 | B10: Sanctuarisation - confidentialite | C10: =COUNTIFS(Verbatims!$A$5:$A$407,C$4,Verbatims!$C$5:$C$407,$A10) | D10: =COUNTIFS(Verbatims!$A$5:$A$407,D$4,Verbatims!$C$5:$C$407,$A10) | E10: =COUNTIFS(Verbatims!$A$5:$A$407,E$4,Verbatims!$C$5:$C$407,$A10) | F10: =COUNTIFS(Verbatims!$A$5:$A$407,F$4,Verbatims!$C$5:$C$407,$A10) | G10: =COUNTIFS(Verbatims!$A$5:$A$407,G$4,Verbatims!$C$5:$C$407,$A10) | H10: =COUNTIFS(Verbatims!$A$5:$A$407,H$4,Verbatims!$C$5:$C$407,$A10) | I10: =COUNTIFS(Verbatims!$A$5:$A$407,I$4,Verbatims!$C$5:$C$407,$A10) | J10: =COUNTIFS(Verbatims!$A$5:$A$407,J$4,Verbatims!$C$5:$C$407,$A10) | K10: =SUM(C10:J10) | L10: =COUNTIF(C10:J10,">0")
A11: A2.2 | B11: Sanctuarisation - jugement | C11: =COUNTIFS(Verbatims!$A$5:$A$407,C$4,Verbatims!$C$5:$C$407,$A11) | D11: =COUNTIFS(Verbatims!$A$5:$A$407,D$4,Verbatims!$C$5:$C$407,$A11) | E11: =COUNTIFS(Verbatims!$A$5:$A$407,E$4,Verbatims!$C$5:$C$407,$A11) | F11: =COUNTIFS(Verbatims!$A$5:$A$407,F$4,Verbatims!$C$5:$C$407,$A11) | G11: =COUNTIFS(Verbatims!$A$5:$A$407,G$4,Verbatims!$C$5:$C$407,$A11) | H11: =COUNTIFS(Verbatims!$A$5:$A$407,H$4,Verbatims!$C$5:$C$407,$A11) | I11: =COUNTIFS(Verbatims!$A$5:$A$407,I$4,Verbatims!$C$5:$C$407,$A11) | J11: =COUNTIFS(Verbatims!$A$5:$A$407,J$4,Verbatims!$C$5:$C$407,$A11) | K11: =SUM(C11:J11) | L11: =COUNTIF(C11:J11,">0")
A12: A2.3 | B12: Sanctuarisation - relation | C12: =COUNTIFS(Verbatims!$A$5:$A$407,C$4,Verbatims!$C$5:$C$407,$A12) | D12: =COUNTIFS(Verbatims!$A$5:$A$407,D$4,Verbatims!$C$5:$C$407,$A12) | E12: =COUNTIFS(Verbatims!$A$5:$A$407,E$4,Verbatims!$C$5:$C$407,$A12) | F12: =COUNTIFS(Verbatims!$A$5:$A$407,F$4,Verbatims!$C$5:$C$407,$A12) | G12: =COUNTIFS(Verbatims!$A$5:$A$407,G$4,Verbatims!$C$5:$C$407,$A12) | H12: =COUNTIFS(Verbatims!$A$5:$A$407,H$4,Verbatims!$C$5:$C$407,$A12) | I12: =COUNTIFS(Verbatims!$A$5:$A$407,I$4,Verbatims!$C$5:$C$407,$A12) | J12: =COUNTIFS(Verbatims!$A$5:$A$407,J$4,Verbatims!$C$5:$C$407,$A12) | K12: =SUM(C12:J12) | L12: =COUNTIF(C12:J12,">0")
A13: A3.1 | B13: Apprentissage autonome | C13: =COUNTIFS(Verbatims!$A$5:$A$407,C$4,Verbatims!$C$5:$C$407,$A13) | D13: =COUNTIFS(Verbatims!$A$5:$A$407,D$4,Verbatims!$C$5:$C$407,$A13) | E13: =COUNTIFS(Verbatims!$A$5:$A$407,E$4,Verbatims!$C$5:$C$407,$A13) | F13: =COUNTIFS(Verbatims!$A$5:$A$407,F$4,Verbatims!$C$5:$C$407,$A13) | G13: =COUNTIFS(Verbatims!$A$5:$A$407,G$4,Verbatims!$C$5:$C$407,$A13) | H13: =COUNTIFS(Verbatims!$A$5:$A$407,H$4,Verbatims!$C$5:$C$407,$A13) | I13: =COUNTIFS(Verbatims!$A$5:$A$407,I$4,Verbatims!$C$5:$C$407,$A13) | J13: =COUNTIFS(Verbatims!$A$5:$A$407,J$4,Verbatims!$C$5:$C$407,$A13) | K13: =SUM(C13:J13) | L13: =COUNTIF(C13:J13,">0")
A14: A3.2 | B14: Transmission entre pairs | C14: =COUNTIFS(Verbatims!$A$5:$A$407,C$4,Verbatims!$C$5:$C$407,$A14) | D14: =COUNTIFS(Verbatims!$A$5:$A$407,D$4,Verbatims!$C$5:$C$407,$A14) | E14: =COUNTIFS(Verbatims!$A$5:$A$407,E$4,Verbatims!$C$5:$C$407,$A14) | F14: =COUNTIFS(Verbatims!$A$5:$A$407,F$4,Verbatims!$C$5:$C$407,$A14) | G14: =COUNTIFS(Verbatims!$A$5:$A$407,G$4,Verbatims!$C$5:$C$407,$A14) | H14: =COUNTIFS(Verbatims!$A$5:$A$407,H$4,Verbatims!$C$5:$C$407,$A14) | I14: =COUNTIFS(Verbatims!$A$5:$A$407,I$4,Verbatims!$C$5:$C$407,$A14) | J14: =COUNTIFS(Verbatims!$A$5:$A$407,J$4,Verbatims!$C$5:$C$407,$A14) | K14: =SUM(C14:J14) | L14: =COUNTIF(C14:J14,">0")
A15: A3.3 | B15: Formation institutionnelle | C15: =COUNTIFS(Verbatims!$A$5:$A$407,C$4,Verbatims!$C$5:$C$407,$A15) | D15: =COUNTIFS(Verbatims!$A$5:$A$407,D$4,Verbatims!$C$5:$C$407,$A15) | E15: =COUNTIFS(Verbatims!$A$5:$A$407,E$4,Verbatims!$C$5:$C$407,$A15) | F15: =COUNTIFS(Verbatims!$A$5:$A$407,F$4,Verbatims!$C$5:$C$407,$A15) | G15: =COUNTIFS(Verbatims!$A$5:$A$407,G$4,Verbatims!$C$5:$C$407,$A15) | H15: =COUNTIFS(Verbatims!$A$5:$A$407,H$4,Verbatims!$C$5:$C$407,$A15) | I15: =COUNTIFS(Verbatims!$A$5:$A$407,I$4,Verbatims!$C$5:$C$407,$A15) | J15: =COUNTIFS(Verbatims!$A$5:$A$407,J$4,Verbatims!$C$5:$C$407,$A15) | K15: =SUM(C15:J15) | L15: =COUNTIF(C15:J15,">0")
A16: A4.1 | B16: Utilite percue | C16: =COUNTIFS(Verbatims!$A$5:$A$407,C$4,Verbatims!$C$5:$C$407,$A16) | D16: =COUNTIFS(Verbatims!$A$5:$A$407,D$4,Verbatims!$C$5:$C$407,$A16) | E16: =COUNTIFS(Verbatims!$A$5:$A$407,E$4,Verbatims!$C$5:$C$407,$A16) | F16: =COUNTIFS(Verbatims!$A$5:$A$407,F$4,Verbatims!$C$5:$C$407,$A16) | G16: =COUNTIFS(Verbatims!$A$5:$A$407,G$4,Verbatims!$C$5:$C$407,$A16) | H16: =COUNTIFS(Verbatims!$A$5:$A$407,H$4,Verbatims!$C$5:$C$407,$A16) | I16: =COUNTIFS(Verbatims!$A$5:$A$407,I$4,Verbatims!$C$5:$C$407,$A16) | J16: =COUNTIFS(Verbatims!$A$5:$A$407,J$4,Verbatims!$C$5:$C$407,$A16) | K16: =SUM(C16:J16) | L16: =COUNTIF(C16:J16,">0")
... A58: T3.3 | B58: Code emergent 3 | C58: =COUNTIFS(Verbatims!$A$5:$A$407,C$4,Verbatims!$C$5:$C$407,$A58) | D58: =COUNTIFS(Verbatims!$A$5:$A$407,D$4,Verbatims!$C$5:$C$407,$A58) | E58: =COUNTIFS(Verbatims!$A$5:$A$407,E$4,Verbatims!$C$5:$C$407,$A58) | F58: =COUNTIFS(Verbatims!$A$5:$A$407,F$4,Verbatims!$C$5:$C$407,$A58) | G58: =COUNTIFS(Verbatims!$A$5:$A$407,G$4,Verbatims!$C$5:$C$407,$A58) | H58: =COUNTIFS(Verbatims!$A$5:$A$407,H$4,Verbatims!$C$5:$C$407,$A58) | I58: =COUNTIFS(Verbatims!$A$5:$A$407,I$4,Verbatims!$C$5:$C$407,$A58) | J58: =COUNTIFS(Verbatims!$A$5:$A$407,J$4,Verbatims!$C$5:$C$407,$A58) | K58: =SUM(C58:J58) | L58: =COUNTIF(C58:J58,">0")
B60: Total des segments codes | C60: =SUM(C5:C58) | D60: =SUM(D5:D58) | E60: =SUM(E5:E58) | F60: =SUM(F5:F58) | G60: =SUM(G5:G58) | H60: =SUM(H5:H58) | I60: =SUM(I5:I58) | J60: =SUM(J5:J58) | K60: =SUM(K5:K58)

Sheet Synthese J-M
A1: Confrontation juniors / encadrants
A2: Ecart = part des encadrants moins part des juniors ayant aborde le code. Parts calculees sur 2 juniors et 3 encadrants. Un ecart marque signale un clivage a exploiter en 4.1 et 4.2.
A4: Code | B4: Intitule | C4: Juniors (nb) | D4: Encadrants (nb) | F4: Part juniors (/2) | G4: Part encadrants (/3) | H4: Ecart
A5: A1.1 | B5: Recherche et veille | C5: =COUNTIF(Matrice!$C5:$F5,">0") | D5: =COUNTIF(Matrice!$G5:$J5,">0") | F5: =IFERROR($C5/2,0) | G5: =IFERROR($D5/3,0) | H5: =$G5-$F5
A6: A1.2 | B6: Synthese et reformulation | C6: =COUNTIF(Matrice!$C6:$F6,">0") | D6: =COUNTIF(Matrice!$G6:$J6,">0") | F6: =IFERROR($C6/2,0) | G6: =IFERROR($D6/3,0) | H6: =$G6-$F6
A7: A1.3 | B7: Premiere redaction | C7: =COUNTIF(Matrice!$C7:$F7,">0") | D7: =COUNTIF(Matrice!$G7:$J7,">0") | F7: =IFERROR($C7/2,0) | G7: =IFERROR($D7/3,0) | H7: =$G7-$F7
A8: A1.4 | B8: Traduction et mise en forme | C8: =COUNTIF(Matrice!$C8:$F8,">0") | D8: =COUNTIF(Matrice!$G8:$J8,">0") | F8: =IFERROR($C8/2,0) | G8: =IFERROR($D8/3,0) | H8: =$G8-$F8
A9: A1.5 | B9: Structuration du raisonnement | C9: =COUNTIF(Matrice!$C9:$F9,">0") | D9: =COUNTIF(Matrice!$G9:$J9,">0") | F9: =IFERROR($C9/2,0) | G9: =IFERROR($D9/3,0) | H9: =$G9-$F9
A10: A2.1 | B10: Sanctuarisation - confidentialite | C10: =COUNTIF(Matrice!$C10:$F10,">0") | D10: =COUNTIF(Matrice!$G10:$J10,">0") | F10: =IFERROR($C10/2,0) | G10: =IFERROR($D10/3,0) | H10: =$G10-$F10
A11: A2.2 | B11: Sanctuarisation - jugement | C11: =COUNTIF(Matrice!$C11:$F11,">0") | D11: =COUNTIF(Matrice!$G11:$J11,">0") | F11: =IFERROR($C11/2,0) | G11: =IFERROR($D11/3,0) | H11: =$G11-$F11
A12: A2.3 | B12: Sanctuarisation - relation | C12: =COUNTIF(Matrice!$C12:$F12,">0") | D12: =COUNTIF(Matrice!$G12:$J12,">0") | F12: =IFERROR($C12/2,0) | G12: =IFERROR($D12/3,0) | H12: =$G12-$F12
A13: A3.1 | B13: Apprentissage autonome | C13: =COUNTIF(Matrice!$C13:$F13,">0") | D13: =COUNTIF(Matrice!$G13:$J13,">0") | F13: =IFERROR($C13/2,0) | G13: =IFERROR($D13/3,0) | H13: =$G13-$F13
A14: A3.2 | B14: Transmission entre pairs | C14: =COUNTIF(Matrice!$C14:$F14,">0") | D14: =COUNTIF(Matrice!$G14:$J14,">0") | F14: =IFERROR($C14/2,0) | G14: =IFERROR($D14/3,0) | H14: =$G14-$F14
A15: A3.3 | B15: Formation institutionnelle | C15: =COUNTIF(Matrice!$C15:$F15,">0") | D15: =COUNTIF(Matrice!$G15:$J15,">0") | F15: =IFERROR($C15/2,0) | G15: =IFERROR($D15/3,0) | H15: =$G15-$F15
A16: A4.1 | B16: Utilite percue | C16: =COUNTIF(Matrice!$C16:$F16,">0") | D16: =COUNTIF(Matrice!$G16:$J16,">0") | F16: =IFERROR($C16/2,0) | G16: =IFERROR($D16/3,0) | H16: =$G16-$F16
... A58: T3.3 | B58: Code emergent 3 | C58: =COUNTIF(Matrice!$C58:$F58,">0") | D58: =COUNTIF(Matrice!$G58:$J58,">0") | F58: =IFERROR($C58/2,0) | G58: =IFERROR($D58/3,0) | H58: =$G58-$F58

Sheet Saturation
A1: Suivi de la saturation theorique
A2: Renseigner la colonne Rang selon l'ordre reel de passation des entretiens, puis lire le nombre de codes distincts. La saturation est atteinte quand un entretien n'apporte plus de code inedit.
A4: Rang de passation | B4: Repondant | C4: Codes distincts mobilises | D4: Codes nouveaux apportes | E4: Commentaire
A5: 1 | B5: J1 | C5: =COUNTIF(Matrice!C$5:C$58,">0") | D5: 27 | E5: Entretien d'ouverture. Fait apparaître l'essentiel de la grille : les cinq axes sont mobilisés dès le premier récit.
A6: 2 | B6: E1 | C6: =COUNTIF(Matrice!G$5:G$58,">0") | D6: 11 | E6: Premier encadrant. Apporte la position de contrôle : vertu formatrice des tâches ingrates, adaptation de la revue après incident, écart entre positions.
A7: 3 | B7: J2 | C7: =COUNTIF(Matrice!D$5:D$58,">0") | D7: 4 | E7: Second junior. Confirme sans ajouter : la grille est stabilisée à ce rang.
A8: 4 | B8: E2 | C8: =COUNTIF(Matrice!H$5:H$58,">0") | D8: 2 | E8: Associé. Deux codes inédits seulement, dont la transparence assumée vis-à-vis du client, isolée dans le corpus.
A9: 5 | B9: E3 | C9: =COUNTIF(Matrice!I$5:I$58,">0") | D9: 4 | E9: Consultant senior en contexte réglementaire strict. Quatre codes inédits, tous liés à la responsabilité et à la crédibilité : la saturation n'est pas atteinte.
B11: Total de codes mobilisés | C11: 48 | E11: Sur les 55 codes de la grille. Six codes ne sont mobilisés par personne, dont B3.2 (appauvrissement de l'interaction junior-encadrant), hypothèse que le corpus contredit.
A15: Colonne 3 : calculee. Colonne 4 : a saisir apres codage de l'entretien.
